{
    "input_path": "keyframes\\0018.jpg",
    "page_index": null,
    "model_settings": {
        "use_doc_preprocessor": false,
        "use_textline_orientation": false
    },
    "dt_polys": [
        [
            [
                288,
                76
            ],
            [
                514,
                78
            ],
            [
                514,
                99
            ],
            [
                288,
                97
            ]
        ],
        [
            [
                302,
                102
            ],
            [
                587,
                102
            ],
            [
                587,
                120
            ],
            [
                302,
                120
            ]
        ],
        [
            [
                301,
                124
            ],
            [
                622,
                125
            ],
            [
                622,
                145
            ],
            [
                301,
                144
            ]
        ],
        [
            [
                303,
                146
            ],
            [
                541,
                146
            ],
            [
                541,
                167
            ],
            [
                303,
                167
            ]
        ],
        [
            [
                302,
                170
            ],
            [
                534,
                170
            ],
            [
                534,
                187
            ],
            [
                302,
                187
            ]
        ],
        [
            [
                301,
                212
            ],
            [
                605,
                214
            ],
            [
                605,
                234
            ],
            [
                301,
                232
            ]
        ],
        [
            [
                302,
                236
            ],
            [
                471,
                236
            ],
            [
                471,
                257
            ],
            [
                302,
                257
            ]
        ],
        [
            [
                573,
                341
            ],
            [
                639,
                341
            ],
            [
                639,
                358
            ],
            [
                573,
                358
            ]
        ]
    ],
    "text_det_params": {
        "limit_side_len": 64,
        "limit_type": "min",
        "thresh": 0.3,
        "max_side_limit": 4000,
        "box_thresh": 0.6,
        "unclip_ratio": 1.5
    },
    "text_type": "general",
    "textline_orientation_angles": [
        -1,
        -1,
        -1,
        -1,
        -1,
        -1,
        -1,
        -1
    ],
    "text_rec_score_thresh": 0.0,
    "return_word_box": false,
    "rec_texts": [
        "AIis the new Electricity",
        "Electricity had once transformed",
        "countless industries:transportation,",
        "manufacturing,healthcare,",
        "communications.and more",
        "AI will now bring about an equally",
        "big transformation.",
        "Andrew Ng"
    ],
    "rec_scores": [
        0.9434787631034851,
        0.960785984992981,
        0.9607456922531128,
        0.9861488342285156,
        0.962211549282074,
        0.9367111921310425,
        0.9835535287857056,
        0.9753104448318481
    ],
    "rec_polys": [
        [
            [
                288,
                76
            ],
            [
                514,
                78
            ],
            [
                514,
                99
            ],
            [
                288,
                97
            ]
        ],
        [
            [
                302,
                102
            ],
            [
                587,
                102
            ],
            [
                587,
                120
            ],
            [
                302,
                120
            ]
        ],
        [
            [
                301,
                124
            ],
            [
                622,
                125
            ],
            [
                622,
                145
            ],
            [
                301,
                144
            ]
        ],
        [
            [
                303,
                146
            ],
            [
                541,
                146
            ],
            [
                541,
                167
            ],
            [
                303,
                167
            ]
        ],
        [
            [
                302,
                170
            ],
            [
                534,
                170
            ],
            [
                534,
                187
            ],
            [
                302,
                187
            ]
        ],
        [
            [
                301,
                212
            ],
            [
                605,
                214
            ],
            [
                605,
                234
            ],
            [
                301,
                232
            ]
        ],
        [
            [
                302,
                236
            ],
            [
                471,
                236
            ],
            [
                471,
                257
            ],
            [
                302,
                257
            ]
        ],
        [
            [
                573,
                341
            ],
            [
                639,
                341
            ],
            [
                639,
                358
            ],
            [
                573,
                358
            ]
        ]
    ],
    "rec_boxes": [
        [
            288,
            76,
            514,
            99
        ],
        [
            302,
            102,
            587,
            120
        ],
        [
            301,
            124,
            622,
            145
        ],
        [
            303,
            146,
            541,
            167
        ],
        [
            302,
            170,
            534,
            187
        ],
        [
            301,
            212,
            605,
            234
        ],
        [
            302,
            236,
            471,
            257
        ],
        [
            573,
            341,
            639,
            358
        ]
    ]
}