{
    "input_path": "keyframes\\0055.jpg",
    "page_index": null,
    "model_settings": {
        "use_doc_preprocessor": false,
        "use_textline_orientation": false
    },
    "dt_polys": [
        [
            [
                45,
                35
            ],
            [
                285,
                37
            ],
            [
                285,
                70
            ],
            [
                45,
                67
            ]
        ],
        [
            [
                47,
                99
            ],
            [
                406,
                99
            ],
            [
                406,
                120
            ],
            [
                47,
                120
            ]
        ],
        [
            [
                46,
                122
            ],
            [
                65,
                122
            ],
            [
                65,
                142
            ],
            [
                46,
                142
            ]
        ],
        [
            [
                84,
                121
            ],
            [
                409,
                123
            ],
            [
                409,
                143
            ],
            [
                84,
                141
            ]
        ],
        [
            [
                46,
                143
            ],
            [
                65,
                143
            ],
            [
                65,
                165
            ],
            [
                46,
                165
            ]
        ],
        [
            [
                86,
                145
            ],
            [
                536,
                145
            ],
            [
                536,
                166
            ],
            [
                86,
                166
            ]
        ],
        [
            [
                87,
                169
            ],
            [
                439,
                169
            ],
            [
                439,
                186
            ],
            [
                87,
                186
            ]
        ],
        [
            [
                46,
                189
            ],
            [
                67,
                189
            ],
            [
                67,
                211
            ],
            [
                46,
                211
            ]
        ],
        [
            [
                86,
                189
            ],
            [
                461,
                189
            ],
            [
                461,
                210
            ],
            [
                86,
                210
            ]
        ],
        [
            [
                476,
                186
            ],
            [
                573,
                180
            ],
            [
                574,
                205
            ],
            [
                477,
                211
            ]
        ],
        [
            [
                46,
                213
            ],
            [
                66,
                213
            ],
            [
                66,
                231
            ],
            [
                46,
                231
            ]
        ],
        [
            [
                86,
                213
            ],
            [
                366,
                213
            ],
            [
                366,
                230
            ],
            [
                86,
                230
            ]
        ],
        [
            [
                482,
                211
            ],
            [
                564,
                206
            ],
            [
                565,
                229
            ],
            [
                483,
                234
            ]
        ],
        [
            [
                573,
                338
            ],
            [
                638,
                341
            ],
            [
                638,
                358
            ],
            [
                573,
                356
            ]
        ]
    ],
    "text_det_params": {
        "limit_side_len": 64,
        "limit_type": "min",
        "thresh": 0.3,
        "max_side_limit": 4000,
        "box_thresh": 0.6,
        "unclip_ratio": 1.5
    },
    "text_type": "general",
    "textline_orientation_angles": [
        -1,
        -1,
        -1,
        -1,
        -1,
        -1,
        -1,
        -1,
        -1,
        -1,
        -1,
        -1,
        -1,
        -1
    ],
    "text_rec_score_thresh": 0.0,
    "return_word_box": false,
    "rec_texts": [
        "What you'lllearn",
        "Courses in this sequence (Specialization):",
        "1.",
        "NeuralNetworks and Deep Learning",
        "2.",
        "Improving Deep NeuralNetworks: Hyperparameter",
        "tuning,Regularization andOptimization",
        "3.",
        "Structuring your Machine Learning project",
        "ton/deu/test",
        "4.",
        "ConvolutionalNeuralNetworks",
        "end-to-end",
        "Andrew Ng"
    ],
    "rec_scores": [
        0.9728606939315796,
        0.9540706872940063,
        0.9841363430023193,
        0.9530037641525269,
        0.9820479154586792,
        0.9581683874130249,
        0.9621540904045105,
        0.9911131858825684,
        0.9545185565948486,
        0.8422064185142517,
        0.9875370264053345,
        0.9941775798797607,
        0.8374407887458801,
        0.9919861555099487
    ],
    "rec_polys": [
        [
            [
                45,
                35
            ],
            [
                285,
                37
            ],
            [
                285,
                70
            ],
            [
                45,
                67
            ]
        ],
        [
            [
                47,
                99
            ],
            [
                406,
                99
            ],
            [
                406,
                120
            ],
            [
                47,
                120
            ]
        ],
        [
            [
                46,
                122
            ],
            [
                65,
                122
            ],
            [
                65,
                142
            ],
            [
                46,
                142
            ]
        ],
        [
            [
                84,
                121
            ],
            [
                409,
                123
            ],
            [
                409,
                143
            ],
            [
                84,
                141
            ]
        ],
        [
            [
                46,
                143
            ],
            [
                65,
                143
            ],
            [
                65,
                165
            ],
            [
                46,
                165
            ]
        ],
        [
            [
                86,
                145
            ],
            [
                536,
                145
            ],
            [
                536,
                166
            ],
            [
                86,
                166
            ]
        ],
        [
            [
                87,
                169
            ],
            [
                439,
                169
            ],
            [
                439,
                186
            ],
            [
                87,
                186
            ]
        ],
        [
            [
                46,
                189
            ],
            [
                67,
                189
            ],
            [
                67,
                211
            ],
            [
                46,
                211
            ]
        ],
        [
            [
                86,
                189
            ],
            [
                461,
                189
            ],
            [
                461,
                210
            ],
            [
                86,
                210
            ]
        ],
        [
            [
                476,
                186
            ],
            [
                573,
                180
            ],
            [
                574,
                205
            ],
            [
                477,
                211
            ]
        ],
        [
            [
                46,
                213
            ],
            [
                66,
                213
            ],
            [
                66,
                231
            ],
            [
                46,
                231
            ]
        ],
        [
            [
                86,
                213
            ],
            [
                366,
                213
            ],
            [
                366,
                230
            ],
            [
                86,
                230
            ]
        ],
        [
            [
                482,
                211
            ],
            [
                564,
                206
            ],
            [
                565,
                229
            ],
            [
                483,
                234
            ]
        ],
        [
            [
                573,
                338
            ],
            [
                638,
                341
            ],
            [
                638,
                358
            ],
            [
                573,
                356
            ]
        ]
    ],
    "rec_boxes": [
        [
            45,
            35,
            285,
            70
        ],
        [
            47,
            99,
            406,
            120
        ],
        [
            46,
            122,
            65,
            142
        ],
        [
            84,
            121,
            409,
            143
        ],
        [
            46,
            143,
            65,
            165
        ],
        [
            86,
            145,
            536,
            166
        ],
        [
            87,
            169,
            439,
            186
        ],
        [
            46,
            189,
            67,
            211
        ],
        [
            86,
            189,
            461,
            210
        ],
        [
            476,
            180,
            574,
            211
        ],
        [
            46,
            213,
            66,
            231
        ],
        [
            86,
            213,
            366,
            230
        ],
        [
            482,
            206,
            565,
            234
        ],
        [
            573,
            338,
            638,
            358
        ]
    ]
}